aws_sns_verifier/__init__.py
aws_sns_verifier/attachments.py
aws_sns_verifier/models.py
aws_sns_verifier/validator.py
aws_sns_verifier-0.1.14.dist-info/METADATA
aws_sns_verifier-0.1.14.dist-info/WHEEL
aws_sns_verifier-0.1.14.dist-info/top_level.txt
aws_sns_verifier-0.1.14.dist-info/RECORD
