Metadata-Version: 2.4
Name: aws-sns-verifier
Version: 0.1.14
Summary: AWS SNS Verifier
Author-email: yagizklc <yagizkilicarslan1@gmail.com>
Requires-Python: >=3.10
Requires-Dist: boto3>=1.40.1
Requires-Dist: cryptography>=45.0.5
Requires-Dist: logfire-api>=4.0.1
Requires-Dist: pydantic>=2.11.7
